connection/__init__.py
connection/bigquery/__init__.py
connection/bigquery/api.py
connection/mongodb/__init__.py
connection/mongodb/api.py
connection/mysql/__init__.py
connection/mysql/api.py
connection_databases-0.1.1.dist-info/LICENSE
connection_databases-0.1.1.dist-info/METADATA
connection_databases-0.1.1.dist-info/WHEEL
connection_databases-0.1.1.dist-info/top_level.txt
connection_databases-0.1.1.dist-info/RECORD
