Metadata-Version: 2.1
Name: connection-databases
Version: 0.1.1
Summary: Package for querying different databases
Home-page: UNKNOWN
Author: Fabio Caffarello
License: UNKNOWN
Platform: UNKNOWN
Requires-Python: >=3.6
Requires-Dist: pandas (>=1.2)
Requires-Dist: SQLAlchemy (>=1.4)
Requires-Dist: dnspython (>=2.1)
Requires-Dist: pymongo (>=3.11)
Requires-Dist: PyMySQL (>=1.0)
Requires-Dist: pybigquery (>=0.5)
Requires-Dist: google-cloud-bigquery (>=2.13google-cloud-bigquery-storage>=2.3)
